curlgoogle/__init__.py
curlgoogle/console.py
curlgoogle/curlgoogledownload.py
curlgoogle/curlgoogleupload.py
curlgoogle/info.py
curlgoogle-0.0.3.dist-info/LICENSE
curlgoogle-0.0.3.dist-info/METADATA
curlgoogle-0.0.3.dist-info/WHEEL
curlgoogle-0.0.3.dist-info/entry_points.txt
curlgoogle-0.0.3.dist-info/top_level.txt
curlgoogle-0.0.3.dist-info/RECORD
